[
  {
    "img": "/assets/images/project/found3.png"
  },
  {
    "img": "/assets/images/project/found4.png"
  },
  {
    "img": "/assets/images/project/found5.png"
  },
  {
    "img": "/assets/images/project/found6.png"
  },
  {
    "img": "/assets/images/project/found7.png"
  },
  {
    "img": "/assets/images/project/found8.png"
  },
  {
    "img": "/assets/images/project/found9.png"
  },
  {
    "img": "/assets/images/project/found10.png"
  },
  {
    "img": "/assets/images/project/found11.png"
  }
]
